[
 {
  "image": "G:\\ai_projects\\nwcb\\website\\docs\\audit\\_up\\bard-gear\\Devil Forged Hide_IL1215.png",
  "id": 4114,
  "dbName": "Devil Forged Hide",
  "dbItemLevel": 1215,
  "dbRatingStats": {
   "Critical Severity": 911,
   "Defense": 911
  },
  "dbPercentStats": {},
  "dbEquipBonuses": [
   {
    "name": "Leader's Guard",
    "stat": null,
    "amount": null,
    "description": "Gain 1000 Defense for each player in your team.",
    "setName": null,
    "pieces": null
   },
   {
    "name": "Devil Hunter",
    "stat": null,
    "amount": null,
    "description": "+1% Damage against Demons.",
    "setName": null,
    "pieces": null
   }
  ]
 },
 {
  "image": "G:\\ai_projects\\nwcb\\website\\docs\\audit\\_up\\bard-gear\\Devil Forged Scalemail_IL1215.png",
  "id": 1407,
  "dbName": "Devil Forged Scalemail",
  "dbItemLevel": 1215,
  "dbRatingStats": {
   "Defense": 911,
   "Deflection": 911
  },
  "dbPercentStats": {
   "Damage against Demons": 1
  },
  "dbEquipBonuses": [
   {
    "name": "Leader's Guard",
    "stat": null,
    "amount": null,
    "description": "Gain 1000 Defense for each player in your team.",
    "setName": null,
    "pieces": null
   },
   {
    "name": "Devil Hunter",
    "stat": null,
    "amount": null,
    "description": "+1% Damage against Demons",
    "setName": null,
    "pieces": null
   }
  ]
 },
 {
  "image": "G:\\ai_projects\\nwcb\\website\\docs\\audit\\_up\\bard-gear\\Dinohide Assault Mederebiya_IL784.png",
  "id": 4443,
  "dbName": "Dinohide Assault Mederebiya",
  "dbItemLevel": 784,
  "dbRatingStats": {
   "Critical Strike": 353,
   "Critical Severity": 235,
   "Defense": 588
  },
  "dbPercentStats": {},
  "dbEquipBonuses": [
   {
    "name": "Challenger's Might",
    "stat": null,
    "amount": null,
    "description": "When in combat with only one enemy, Power +1500.",
    "setName": null,
    "pieces": null
   }
  ]
 },
 {
  "image": "G:\\ai_projects\\nwcb\\website\\docs\\audit\\_up\\bard-gear\\Dinohide Raid Mederebiya_IL784.png",
  "id": 4439,
  "dbName": "Dinohide Raid Mederebiya",
  "dbItemLevel": 784,
  "dbRatingStats": {
   "Combat Advantage": 235,
   "Critical Strike": 353,
   "Defense": 588
  },
  "dbPercentStats": {},
  "dbEquipBonuses": [
   {
    "name": "Challenger's Might",
    "stat": null,
    "amount": null,
    "description": "When in combat with only one enemy, Power +1500.",
    "setName": null,
    "pieces": null
   }
  ]
 },
 {
  "image": "G:\\ai_projects\\nwcb\\website\\docs\\audit\\_up\\bard-gear\\Divine Raid Surcoat_IL1230 (2).png",
  "id": 4099,
  "dbName": "Divine Raid Surcoat",
  "dbItemLevel": 1230,
  "dbRatingStats": {
   "Critical Severity": 922,
   "Defense": 922
  },
  "dbPercentStats": {},
  "dbEquipBonuses": [
   {
    "name": "Critical Remedy",
    "stat": null,
    "amount": null,
    "description": "Whenever you Critically Strike with your Powers, you have a 10% chance to restore 5% of your Maximum Hit Points. (5s CD)",
    "setName": null,
    "pieces": null
   }
  ]
 },
 {
  "image": "G:\\ai_projects\\nwcb\\website\\docs\\audit\\_up\\bard-gear\\Divine Raid Surcoat_IL1230.png",
  "id": 4099,
  "dbName": "Divine Raid Surcoat",
  "dbItemLevel": 1230,
  "dbRatingStats": {
   "Critical Severity": 922,
   "Defense": 922
  },
  "dbPercentStats": {},
  "dbEquipBonuses": [
   {
    "name": "Critical Remedy",
    "stat": null,
    "amount": null,
    "description": "Whenever you Critically Strike with your Powers, you have a 10% chance to restore 5% of your Maximum Hit Points. (5s CD)",
    "setName": null,
    "pieces": null
   }
  ]
 },
 {
  "image": "G:\\ai_projects\\nwcb\\website\\docs\\audit\\_up\\bard-gear\\Divine Restoration Surcoat_IL1230.png",
  "id": 3398,
  "dbName": "Divine Restoration Surcoat",
  "dbItemLevel": 1230,
  "dbRatingStats": {
   "Defense": 922,
   "Deflection": 922
  },
  "dbPercentStats": {},
  "dbEquipBonuses": [
   {
    "name": "Critical Remedy",
    "stat": null,
    "amount": null,
    "description": "Whenever you Critically Strike with your Powers, you have a 10% chance to restore 5% of your Maximum Hit Points. This effect may only occur once every 5 seconds.",
    "setName": null,
    "pieces": null
   }
  ]
 },
 {
  "image": "G:\\ai_projects\\nwcb\\website\\docs\\audit\\_up\\bard-gear\\Dragonflight Assault Vest_IL588.png",
  "id": 4572,
  "dbName": "Dragonflight Assault Vest",
  "dbItemLevel": 588,
  "dbRatingStats": {
   "Accuracy": 265,
   "Critical Severity": 176,
   "Defense": 441
  },
  "dbPercentStats": {},
  "dbEquipBonuses": [
   {
    "name": null,
    "stat": "Max HP",
    "amount": 3000,
    "description": "2 of Set: +3,000 Maximum Hit Points. 3 of Set: +500 Power.",
    "setName": "Dragonflight",
    "pieces": 2
   }
  ]
 },
 {
  "image": "G:\\ai_projects\\nwcb\\website\\docs\\audit\\_up\\bard-gear\\Dragonflight Raid Vest_IL588.png",
  "id": 4569,
  "dbName": "Dragonflight Raid Vest",
  "dbItemLevel": 588,
  "dbRatingStats": {
   "Accuracy": 265,
   "Combat Advantage": 176,
   "Defense": 441
  },
  "dbPercentStats": {},
  "dbEquipBonuses": [
   {
    "name": null,
    "stat": "Max HP",
    "amount": 3000,
    "description": "2 of Set: +3,000 Maximum Hit Points. 3 of Set: +500 Power.",
    "setName": "Dragonflight",
    "pieces": 2
   }
  ]
 },
 {
  "image": "G:\\ai_projects\\nwcb\\website\\docs\\audit\\_up\\bard-gear\\Dragonhide Jacket_IL1900 (2).png",
  "id": 4020,
  "dbName": "Dragonhide Jacket",
  "dbItemLevel": 1900,
  "dbRatingStats": {
   "Critical Severity": 1140,
   "Defense": 855,
   "Control Bonus": 855
  },
  "dbPercentStats": {},
  "dbEquipBonuses": [
   {
    "name": "Leader's Power",
    "stat": null,
    "amount": null,
    "description": "Gain 1000 Power and Critical Strike for each player in your team.",
    "setName": null,
    "pieces": null
   }
  ]
 },
 {
  "image": "G:\\ai_projects\\nwcb\\website\\docs\\audit\\_up\\bard-gear\\Dragonhide Jacket_IL1900.png",
  "id": 4020,
  "dbName": "Dragonhide Jacket",
  "dbItemLevel": 1900,
  "dbRatingStats": {
   "Critical Severity": 1140,
   "Defense": 855,
   "Control Bonus": 855
  },
  "dbPercentStats": {},
  "dbEquipBonuses": [
   {
    "name": "Leader's Power",
    "stat": null,
    "amount": null,
    "description": "Gain 1000 Power and Critical Strike for each player in your team.",
    "setName": null,
    "pieces": null
   }
  ]
 },
 {
  "image": "G:\\ai_projects\\nwcb\\website\\docs\\audit\\_up\\bard-gear\\Dragonhide Raiment_IL1900.png",
  "id": 3304,
  "dbName": "Dragonhide Raiment",
  "dbItemLevel": 1900,
  "dbRatingStats": {
   "Critical Severity": 1140,
   "Defense": 855,
   "Deflection": 855
  },
  "dbPercentStats": {},
  "dbEquipBonuses": [
   {
    "name": "Leader's Power",
    "stat": null,
    "amount": null,
    "description": "Gain 1000 Power and Outgoing Healing for each player in your team.",
    "setName": null,
    "pieces": null
   }
  ]
 },
 {
  "image": "G:\\ai_projects\\nwcb\\website\\docs\\audit\\_up\\bard-gear\\Drowcraft Vest_IL567.png",
  "id": 4376,
  "dbName": "Drowcraft Vest",
  "dbItemLevel": 567,
  "dbRatingStats": {
   "Accuracy": 170,
   "Combat Advantage": 255,
   "Defense": 425
  },
  "dbPercentStats": {},
  "dbEquipBonuses": []
 },
 {
  "image": "G:\\ai_projects\\nwcb\\website\\docs\\audit\\_up\\bard-gear\\Dungeon Raider's Hide_IL940 (2).png",
  "id": 4143,
  "dbName": "Dungeon Raider's Hide",
  "dbItemLevel": 940,
  "dbRatingStats": {
   "Critical Severity": 705,
   "Defense": 705
  },
  "dbPercentStats": {},
  "dbEquipBonuses": [
   {
    "name": "Warden's Defense",
    "stat": null,
    "amount": null,
    "description": "When damaged for more than 10% of Max HP in a single blow, gain 5% Defense for 10s.",
    "setName": null,
    "pieces": null
   }
  ]
 },
 {
  "image": "G:\\ai_projects\\nwcb\\website\\docs\\audit\\_up\\bard-gear\\Dungeon Raider's Hide_IL940.png",
  "id": 4143,
  "dbName": "Dungeon Raider's Hide",
  "dbItemLevel": 940,
  "dbRatingStats": {
   "Critical Severity": 705,
   "Defense": 705
  },
  "dbPercentStats": {},
  "dbEquipBonuses": [
   {
    "name": "Warden's Defense",
    "stat": null,
    "amount": null,
    "description": "When damaged for more than 10% of Max HP in a single blow, gain 5% Defense for 10s.",
    "setName": null,
    "pieces": null
   }
  ]
 },
 {
  "image": "G:\\ai_projects\\nwcb\\website\\docs\\audit\\_up\\bard-gear\\Dungeon Raider's Scalemail_IL940.png",
  "id": 1593,
  "dbName": "Dungeon Raider's Scalemail",
  "dbItemLevel": 940,
  "dbRatingStats": {
   "Defense": 705,
   "Deflection": 705
  },
  "dbPercentStats": {},
  "dbEquipBonuses": [
   {
    "name": "Warden's Defense",
    "stat": null,
    "amount": null,
    "description": "Whenever you are damaged for more than 10% of your Maximum Hit Points in a single blow, you gain 5% Defense for 10 seconds.",
    "setName": null,
    "pieces": null
   }
  ]
 },
 {
  "image": "G:\\ai_projects\\nwcb\\website\\docs\\audit\\_up\\bard-gear\\Dusk Assault Vest_IL1175.png",
  "id": 4372,
  "dbName": "Dusk Assault Vest",
  "dbItemLevel": 1175,
  "dbRatingStats": {
   "Critical Strike": 529,
   "Critical Severity": 352,
   "Defense": 881
  },
  "dbPercentStats": {},
  "dbEquipBonuses": [
   {
    "name": null,
    "stat": "Max HP",
    "amount": 5000,
    "description": "2 of Set: +5,000 Max HP, +1% Power, +1% Defense. Wanderer's Vigor: not in party, regenerate 2000 HP every 3s.",
    "setName": "Dusk",
    "pieces": 2
   }
  ]
 },
 {
  "image": "G:\\ai_projects\\nwcb\\website\\docs\\audit\\_up\\bard-gear\\Dusk Raid Vest_IL1175.png",
  "id": 4368,
  "dbName": "Dusk Raid Vest",
  "dbItemLevel": 1175,
  "dbRatingStats": {
   "Accuracy": 529,
   "Combat Advantage": 352,
   "Defense": 881
  },
  "dbPercentStats": {},
  "dbEquipBonuses": [
   {
    "name": null,
    "stat": "Max HP",
    "amount": 5000,
    "description": "2 of Set: +5,000 Max HP, +1% Power, +1% Defense. Wanderer's Vigor: when not in a party, regenerate 2000 HP every 3s. 4 of Set: On Stronghold map, you and allies gain +5 Movement Speed.",
    "setName": "Dusk",
    "pieces": 2
   }
  ]
 },
 {
  "image": "G:\\ai_projects\\nwcb\\website\\docs\\audit\\_up\\bard-gear\\Elegant Leathers of Halaster's Successor_IL1010 (2).png",
  "id": 4123,
  "dbName": "Elegant Leathers of Halaster's Successor",
  "dbItemLevel": 1010,
  "dbRatingStats": {
   "Critical Severity": 758,
   "Defense": 758
  },
  "dbPercentStats": {},
  "dbEquipBonuses": [
   {
    "name": "Gladiator's Guard",
    "stat": null,
    "amount": null,
    "description": "For every 5 seconds you are in combat, you gain 0.5% Defense, to the max of 6%.",
    "setName": null,
    "pieces": null
   }
  ]
 },
 {
  "image": "G:\\ai_projects\\nwcb\\website\\docs\\audit\\_up\\bard-gear\\Elegant Leathers of Halaster's Successor_IL1010.png",
  "id": 4123,
  "dbName": "Elegant Leathers of Halaster's Successor",
  "dbItemLevel": 1010,
  "dbRatingStats": {
   "Critical Severity": 758,
   "Defense": 758
  },
  "dbPercentStats": {},
  "dbEquipBonuses": [
   {
    "name": "Gladiator's Guard",
    "stat": null,
    "amount": null,
    "description": "For every 5 seconds you are in combat, you gain 0.5% Defense, to the max of 6%.",
    "setName": null,
    "pieces": null
   }
  ]
 },
 {
  "image": "G:\\ai_projects\\nwcb\\website\\docs\\audit\\_up\\bard-gear\\Elegant Leathers of the Successor_IL990.png",
  "id": 4127,
  "dbName": "Elegant Leathers of the Successor",
  "dbItemLevel": 990,
  "dbRatingStats": {
   "Critical Severity": 742,
   "Defense": 742
  },
  "dbPercentStats": {},
  "dbEquipBonuses": [
   {
    "name": "Gladiator's Guard",
    "stat": null,
    "amount": null,
    "description": "For every 5 seconds you are in combat, you gain 0.5% Defense, to the max of 6%.",
    "setName": null,
    "pieces": null
   }
  ]
 },
 {
  "image": "G:\\ai_projects\\nwcb\\website\\docs\\audit\\_up\\bard-gear\\Elemental Dragonflight Assault Vest_IL596.png",
  "id": 4581,
  "dbName": "Elemental Dragonflight Assault Vest",
  "dbItemLevel": 596,
  "dbRatingStats": {
   "Accuracy": 268,
   "Critical Severity": 179,
   "Defense": 447
  },
  "dbPercentStats": {},
  "dbEquipBonuses": [
   {
    "name": null,
    "stat": "Max HP",
    "amount": 3000,
    "description": "2 of Set: +3,000 Maximum Hit Points. 3 of Set: +500 Power.",
    "setName": "Dragonflight",
    "pieces": 2
   }
  ]
 },
 {
  "image": "G:\\ai_projects\\nwcb\\website\\docs\\audit\\_up\\bard-gear\\Elemental Dragonflight Raid Vest_IL596.png",
  "id": 4577,
  "dbName": "Elemental Dragonflight Raid Vest",
  "dbItemLevel": 596,
  "dbRatingStats": {
   "Accuracy": 268,
   "Combat Advantage": 179,
   "Defense": 447
  },
  "dbPercentStats": {},
  "dbEquipBonuses": [
   {
    "name": null,
    "stat": "Max HP",
    "amount": 3000,
    "description": "2 of Set: +3,000 Maximum Hit Points. 3 of Set: +500 Power.",
    "setName": "Dragonflight",
    "pieces": 2
   }
  ]
 },
 {
  "image": "G:\\ai_projects\\nwcb\\website\\docs\\audit\\_up\\bard-gear\\Elemental Drowcraft Assault Vest_IL588.png",
  "id": 4384,
  "dbName": "Elemental Drowcraft Assault Vest",
  "dbItemLevel": 588,
  "dbRatingStats": {
   "Combat Advantage": 265,
   "Critical Severity": 176,
   "Defense": 441
  },
  "dbPercentStats": {},
  "dbEquipBonuses": []
 },
 {
  "image": "G:\\ai_projects\\nwcb\\website\\docs\\audit\\_up\\bard-gear\\Elemental Drowcraft Raid Vest_IL588.png",
  "id": 4380,
  "dbName": "Elemental Drowcraft Raid Vest",
  "dbItemLevel": 588,
  "dbRatingStats": {
   "Accuracy": 176,
   "Combat Advantage": 265,
   "Defense": 441
  },
  "dbPercentStats": {},
  "dbEquipBonuses": []
 }
]