[
 {
  "image": "G:\\ai_projects\\nwcb\\website\\docs\\audit\\companions\\_up\\c048.png",
  "src": "Screenshot 2026-03-26 12-04-56.png"
 },
 {
  "image": "G:\\ai_projects\\nwcb\\website\\docs\\audit\\companions\\_up\\c049.png",
  "src": "Screenshot 2026-03-26 12-05-00.png"
 },
 {
  "image": "G:\\ai_projects\\nwcb\\website\\docs\\audit\\companions\\_up\\c050.png",
  "src": "Screenshot 2026-03-26 12-05-03.png"
 },
 {
  "image": "G:\\ai_projects\\nwcb\\website\\docs\\audit\\companions\\_up\\c051.png",
  "src": "Screenshot 2026-03-26 12-05-07.png"
 },
 {
  "image": "G:\\ai_projects\\nwcb\\website\\docs\\audit\\companions\\_up\\c052.png",
  "src": "Screenshot 2026-03-26 12-05-10.png"
 },
 {
  "image": "G:\\ai_projects\\nwcb\\website\\docs\\audit\\companions\\_up\\c053.png",
  "src": "Screenshot 2026-03-26 12-05-13.png"
 },
 {
  "image": "G:\\ai_projects\\nwcb\\website\\docs\\audit\\companions\\_up\\c054.png",
  "src": "Screenshot 2026-03-26 12-05-16.png"
 },
 {
  "image": "G:\\ai_projects\\nwcb\\website\\docs\\audit\\companions\\_up\\c055.png",
  "src": "Screenshot 2026-03-26 12-05-25.png"
 }
]