[
 {
  "image": "G:\\ai_projects\\nwcb\\website\\docs\\audit\\_up\\wizard-gear\\Drowned Orb_IL600.png",
  "id": 5591,
  "dbName": "Drowned Orb",
  "dbItemLevel": 600,
  "dbRatingStats": {
   "Accuracy": 225,
   "Combat Advantage": 450,
   "Critical Strike": 225
  },
  "dbPercentStats": {},
  "dbEquipBonuses": []
 },
 {
  "image": "G:\\ai_projects\\nwcb\\website\\docs\\audit\\_up\\wizard-gear\\Drowned Talisman_IL300.png",
  "id": 5592,
  "dbName": "Drowned Talisman",
  "dbItemLevel": 300,
  "dbRatingStats": {
   "Accuracy": 112,
   "Combat Advantage": 225,
   "Critical Strike": 112
  },
  "dbPercentStats": {},
  "dbEquipBonuses": []
 },
 {
  "image": "G:\\ai_projects\\nwcb\\website\\docs\\audit\\_up\\wizard-gear\\Drowned Talisman_IL400.png",
  "id": 5593,
  "dbName": "Drowned Talisman",
  "dbItemLevel": 400,
  "dbRatingStats": {
   "Accuracy": 150,
   "Combat Advantage": 300,
   "Critical Strike": 150
  },
  "dbPercentStats": {},
  "dbEquipBonuses": []
 },
 {
  "image": "G:\\ai_projects\\nwcb\\website\\docs\\audit\\_up\\wizard-gear\\Drowned Talisman_IL500.png",
  "id": 5594,
  "dbName": "Drowned Talisman",
  "dbItemLevel": 500,
  "dbRatingStats": {
   "Accuracy": 188,
   "Combat Advantage": 375,
   "Critical Strike": 188
  },
  "dbPercentStats": {},
  "dbEquipBonuses": []
 },
 {
  "image": "G:\\ai_projects\\nwcb\\website\\docs\\audit\\_up\\wizard-gear\\Drowned Talisman_IL600.png",
  "id": 5595,
  "dbName": "Drowned Talisman",
  "dbItemLevel": 600,
  "dbRatingStats": {
   "Accuracy": 225,
   "Combat Advantage": 450,
   "Critical Strike": 225
  },
  "dbPercentStats": {},
  "dbEquipBonuses": []
 },
 {
  "image": "G:\\ai_projects\\nwcb\\website\\docs\\audit\\_up\\wizard-gear\\Earthen Orb_IL300.png",
  "id": 5679,
  "dbName": "Earthen Orb",
  "dbItemLevel": 300,
  "dbRatingStats": {
   "Accuracy": 112,
   "Combat Advantage": 225,
   "Critical Strike": 112
  },
  "dbPercentStats": {},
  "dbEquipBonuses": []
 },
 {
  "image": "G:\\ai_projects\\nwcb\\website\\docs\\audit\\_up\\wizard-gear\\Earthen Orb_IL400.png",
  "id": 5680,
  "dbName": "Earthen Orb",
  "dbItemLevel": 400,
  "dbRatingStats": {
   "Accuracy": 150,
   "Combat Advantage": 300,
   "Critical Strike": 150
  },
  "dbPercentStats": {},
  "dbEquipBonuses": []
 },
 {
  "image": "G:\\ai_projects\\nwcb\\website\\docs\\audit\\_up\\wizard-gear\\Earthen Orb_IL500.png",
  "id": 5681,
  "dbName": "Earthen Orb",
  "dbItemLevel": 500,
  "dbRatingStats": {
   "Accuracy": 188,
   "Combat Advantage": 375,
   "Critical Strike": 188
  },
  "dbPercentStats": {},
  "dbEquipBonuses": []
 },
 {
  "image": "G:\\ai_projects\\nwcb\\website\\docs\\audit\\_up\\wizard-gear\\Earthen Orb_IL600.png",
  "id": 5682,
  "dbName": "Earthen Orb",
  "dbItemLevel": 600,
  "dbRatingStats": {
   "Accuracy": 225,
   "Combat Advantage": 450,
   "Critical Strike": 225
  },
  "dbPercentStats": {},
  "dbEquipBonuses": []
 },
 {
  "image": "G:\\ai_projects\\nwcb\\website\\docs\\audit\\_up\\wizard-gear\\Earthen Talisman_IL300.png",
  "id": 5683,
  "dbName": "Earthen Talisman",
  "dbItemLevel": 300,
  "dbRatingStats": {
   "Accuracy": 112,
   "Combat Advantage": 225,
   "Critical Strike": 112
  },
  "dbPercentStats": {},
  "dbEquipBonuses": []
 },
 {
  "image": "G:\\ai_projects\\nwcb\\website\\docs\\audit\\_up\\wizard-gear\\Earthen Talisman_IL400.png",
  "id": 5802,
  "dbName": "Earthen Talisman",
  "dbItemLevel": 400,
  "dbRatingStats": {
   "Accuracy": 150,
   "Combat Advantage": 300,
   "Critical Strike": 150
  },
  "dbPercentStats": {},
  "dbEquipBonuses": []
 },
 {
  "image": "G:\\ai_projects\\nwcb\\website\\docs\\audit\\_up\\wizard-gear\\Earthen Talisman_IL500.png",
  "id": 5684,
  "dbName": "Earthen Talisman",
  "dbItemLevel": 500,
  "dbRatingStats": {
   "Accuracy": 188,
   "Combat Advantage": 375,
   "Critical Strike": 188
  },
  "dbPercentStats": {},
  "dbEquipBonuses": []
 },
 {
  "image": "G:\\ai_projects\\nwcb\\website\\docs\\audit\\_up\\wizard-gear\\Earthen Talisman_IL600.png",
  "id": 5685,
  "dbName": "Earthen Talisman",
  "dbItemLevel": 600,
  "dbRatingStats": {
   "Accuracy": 225,
   "Combat Advantage": 450,
   "Critical Strike": 225
  },
  "dbPercentStats": {},
  "dbEquipBonuses": []
 },
 {
  "image": "G:\\ai_projects\\nwcb\\website\\docs\\audit\\_up\\wizard-gear\\Elemental Fire Talisman_IL300.png",
  "id": 5779,
  "dbName": "Elemental Fire Talisman",
  "dbItemLevel": 300,
  "dbRatingStats": {
   "Accuracy": 150,
   "Combat Advantage": 150,
   "Critical Strike": 150
  },
  "dbPercentStats": {},
  "dbEquipBonuses": []
 },
 {
  "image": "G:\\ai_projects\\nwcb\\website\\docs\\audit\\_up\\wizard-gear\\Exalted Bonepicker_IL350.png",
  "id": 5704,
  "dbName": "Exalted Bonepicker",
  "dbItemLevel": 350,
  "dbRatingStats": {
   "Accuracy": 131,
   "Combat Advantage": 262,
   "Critical Strike": 131
  },
  "dbPercentStats": {},
  "dbEquipBonuses": []
 },
 {
  "image": "G:\\ai_projects\\nwcb\\website\\docs\\audit\\_up\\wizard-gear\\Exalted Bonepicker_IL500.png",
  "id": 5705,
  "dbName": "Exalted Bonepicker",
  "dbItemLevel": 500,
  "dbRatingStats": {
   "Accuracy": 188,
   "Combat Advantage": 375,
   "Critical Strike": 188
  },
  "dbPercentStats": {},
  "dbEquipBonuses": []
 },
 {
  "image": "G:\\ai_projects\\nwcb\\website\\docs\\audit\\_up\\wizard-gear\\Exalted Bonepicker_IL650.png",
  "id": 5706,
  "dbName": "Exalted Bonepicker",
  "dbItemLevel": 650,
  "dbRatingStats": {
   "Accuracy": 244,
   "Combat Advantage": 488,
   "Critical Strike": 244
  },
  "dbPercentStats": {},
  "dbEquipBonuses": []
 },
 {
  "image": "G:\\ai_projects\\nwcb\\website\\docs\\audit\\_up\\wizard-gear\\Exalted Bonepicker_IL800.png",
  "id": 5707,
  "dbName": "Exalted Bonepicker",
  "dbItemLevel": 800,
  "dbRatingStats": {
   "Accuracy": 300,
   "Combat Advantage": 600,
   "Critical Strike": 300
  },
  "dbPercentStats": {},
  "dbEquipBonuses": []
 },
 {
  "image": "G:\\ai_projects\\nwcb\\website\\docs\\audit\\_up\\wizard-gear\\Exalted Bonesnapper_IL350.png",
  "id": 5708,
  "dbName": "Exalted Bonesnapper",
  "dbItemLevel": 350,
  "dbRatingStats": {
   "Accuracy": 131,
   "Combat Advantage": 262,
   "Critical Strike": 131
  },
  "dbPercentStats": {},
  "dbEquipBonuses": []
 },
 {
  "image": "G:\\ai_projects\\nwcb\\website\\docs\\audit\\_up\\wizard-gear\\Exalted Bonesnapper_IL500.png",
  "id": 5709,
  "dbName": "Exalted Bonesnapper",
  "dbItemLevel": 500,
  "dbRatingStats": {
   "Accuracy": 188,
   "Combat Advantage": 375,
   "Critical Strike": 188
  },
  "dbPercentStats": {},
  "dbEquipBonuses": []
 },
 {
  "image": "G:\\ai_projects\\nwcb\\website\\docs\\audit\\_up\\wizard-gear\\Exalted Bonesnapper_IL650.png",
  "id": 5710,
  "dbName": "Exalted Bonesnapper",
  "dbItemLevel": 650,
  "dbRatingStats": {
   "Accuracy": 244,
   "Combat Advantage": 488,
   "Critical Strike": 244
  },
  "dbPercentStats": {},
  "dbEquipBonuses": []
 },
 {
  "image": "G:\\ai_projects\\nwcb\\website\\docs\\audit\\_up\\wizard-gear\\Exalted Bonesnapper_IL800.png",
  "id": 5711,
  "dbName": "Exalted Bonesnapper",
  "dbItemLevel": 800,
  "dbRatingStats": {
   "Accuracy": 300,
   "Combat Advantage": 600,
   "Critical Strike": 300
  },
  "dbPercentStats": {},
  "dbEquipBonuses": []
 },
 {
  "image": "G:\\ai_projects\\nwcb\\website\\docs\\audit\\_up\\wizard-gear\\Exalted Fanged Quiilpia_IL400.png",
  "id": 5720,
  "dbName": "Exalted Fanged Quiilpia",
  "dbItemLevel": 400,
  "dbRatingStats": {
   "Accuracy": 150,
   "Combat Advantage": 300,
   "Critical Strike": 150
  },
  "dbPercentStats": {},
  "dbEquipBonuses": []
 },
 {
  "image": "G:\\ai_projects\\nwcb\\website\\docs\\audit\\_up\\wizard-gear\\Exalted Fanged Quiilpia_IL550.png",
  "id": 5721,
  "dbName": "Exalted Fanged Quiilpia",
  "dbItemLevel": 550,
  "dbRatingStats": {
   "Accuracy": 206,
   "Combat Advantage": 412,
   "Critical Strike": 206
  },
  "dbPercentStats": {},
  "dbEquipBonuses": []
 },
 {
  "image": "G:\\ai_projects\\nwcb\\website\\docs\\audit\\_up\\wizard-gear\\Exalted Fanged Quiilpia_IL700.png",
  "id": 5722,
  "dbName": "Exalted Fanged Quiilpia",
  "dbItemLevel": 700,
  "dbRatingStats": {
   "Accuracy": 262,
   "Combat Advantage": 525,
   "Critical Strike": 262
  },
  "dbPercentStats": {},
  "dbEquipBonuses": []
 }
]